xpipe/__init__.py
xpipe/_version.py
xpipe/core.py
xpipe/utils.py
xpipe/tests/__init__.py
xpipe/tests/conftest.py
xpipe/tests/test_core.py
xpipe/tests/test_utils.py
xas_pipeline-0.post0.dev11.dist-info/AUTHORS.rst
xas_pipeline-0.post0.dev11.dist-info/LICENSE
xas_pipeline-0.post0.dev11.dist-info/METADATA
xas_pipeline-0.post0.dev11.dist-info/WHEEL
xas_pipeline-0.post0.dev11.dist-info/entry_points.txt
xas_pipeline-0.post0.dev11.dist-info/top_level.txt
xas_pipeline-0.post0.dev11.dist-info/RECORD
