Metadata-Version: 2.1
Name: xas-pipeline
Version: 0.post0.dev11
Summary: A data pipeline for processing XAS data
Home-page: https://github.com/zhul9311/xas-data-pipeline
Author: Zhu Liang
Author-email: zliang@bnl.gov
License: BSD (3-clause)
Platform: UNKNOWN
Classifier: Development Status :: 2 - Pre-Alpha
Classifier: Natural Language :: English
Classifier: Programming Language :: Python :: 3
Requires-Python: >=3.7
License-File: LICENSE
License-File: AUTHORS.rst
Requires-Dist: numpy
Requires-Dist: matplotlib
Requires-Dist: scipy
Requires-Dist: pandas
Requires-Dist: sklearn
Requires-Dist: Ipython
Requires-Dist: h5py
